pyISARICBasics/__init__.py
pyISARICBasics/domain.py
pyISARICBasics/functions.py
pyISARICBasics-1.0.4.dist-info/METADATA
pyISARICBasics-1.0.4.dist-info/WHEEL
pyISARICBasics-1.0.4.dist-info/top_level.txt
pyISARICBasics-1.0.4.dist-info/RECORD
