Metadata-Version: 2.1
Name: pyISARICBasics
Version: 1.0.4
Summary: A python package for SQLite database creation and some basic data processing
Home-page: https://github.com/KyleYoung1997/pyIsaricBasics
Author: Kyle G Young
Author-email: kyle.young1@uq.net.au
License: UNKNOWN
Project-URL: Bug Reports, https://github.com/KyleYoung1997/pyIsaricBasics/issues
Project-URL: Source, https://github.com/KyleYoung1997/pyIsaricBasics
Keywords: sample,setuptools,development
Platform: UNKNOWN
Classifier: Development Status :: 3 - Alpha
Classifier: Intended Audience :: Developers
Classifier: License :: OSI Approved :: MIT License
Classifier: Programming Language :: Python :: 3.8
Classifier: Programming Language :: Python :: 3.9
Classifier: Programming Language :: Python :: 3.10
Classifier: Programming Language :: Python :: 3 :: Only
Requires-Python: >=3.6, <4
Requires-Dist: jupyter
Requires-Dist: pandas
Requires-Dist: numpy
